pynats/__init__.py
pynats/client.py
pynats/exceptions.py
pynats/nuid.py
nats_python-0.8.0.dist-info/LICENSE
nats_python-0.8.0.dist-info/WHEEL
nats_python-0.8.0.dist-info/METADATA
nats_python-0.8.0.dist-info/RECORD
