Metadata-Version: 2.1
Name: nats-python
Version: 0.8.0
Summary: Python client for NATS messaging system
Home-page: https://github.com/Gr1N/nats-python
License: MIT
Keywords: nats,nats-client,messaging
Author: Nikita Grishko
Author-email: gr1n@protonmail.com
Requires-Python: >=3.6,<4.0
Classifier: License :: OSI Approved :: MIT License
Classifier: Programming Language :: Python :: 3
Classifier: Programming Language :: Python :: 3.6
Classifier: Programming Language :: Python :: 3.7
Classifier: Programming Language :: Python :: 3.8
Classifier: Topic :: Software Development :: Libraries :: Python Modules
Requires-Dist: dataclasses (>=0.6.0); python_version >= "3.6" and python_version < "3.7"
Project-URL: Repository, https://github.com/Gr1N/nats-python
